<?xml version="1.0" encoding="UTF-8"?>
<objects serializationModel="Studio.02.02.00">
	<object class="AudioFile" id="{56d6b5e9-d128-4ea2-9ce4-def4c7edc214}">
		<property name="assetPath">
			<value>GlideCar 3.wav</value>
		</property>
		<property name="frequencyInKHz">
			<value>48</value>
		</property>
		<property name="channelCount">
			<value>2</value>
		</property>
		<property name="length">
			<value>1.1398541666666666</value>
		</property>
		<relationship name="masterAssetFolder">
			<destination>{74847e29-222c-4246-8e01-ddec005aac00}</destination>
		</relationship>
	</object>
</objects>
